jsonschema2pydantic/__init__.py
jsonschema2pydantic/generator.py
jsonschema2pydantic-0.1.3.dist-info/METADATA
jsonschema2pydantic-0.1.3.dist-info/WHEEL
jsonschema2pydantic-0.1.3.dist-info/licenses/LICENSE
jsonschema2pydantic-0.1.3.dist-info/RECORD
