Metadata-Version: 2.4
Name: jsonschema2pydantic
Version: 0.1.3
Summary: Convert jsonschema to pydantic model
Author-email: rostyslav <rostmoguchiy@gmail.com>
License-Expression: MIT
License-File: LICENSE
Requires-Python: >=3.10
Requires-Dist: pydantic>=2.11.7
